jay_lance-0.38.2.dist-info/METADATA
jay_lance-0.38.2.dist-info/WHEEL
jay_lance-0.38.2.dist-info/licenses/LICENSE
lance/__init__.py
lance/_arrow/__init__.py
lance/_arrow/bf16.py
lance/_datagen.py
lance/_dataset/__init__.py
lance/_dataset/cache.py
lance/_dataset/sharded_batch_iterator.py
lance/arrow.py
lance/blob.py
lance/commit.py
lance/conftest.py
lance/dataset.py
lance/debug.py
lance/dependencies.py
lance/download.py
lance/file.py
lance/fragment.py
lance/hf.py
lance/indices/__init__.py
lance/indices/builder.py
lance/indices/ivf.py
lance/indices/pq.py
lance/lance.abi3.so
lance/lance/__init__.pyi
lance/lance/datagen/__init__.pyi
lance/lance/debug.pyi
lance/lance/fragment.pyi
lance/lance/indices/__init__.pyi
lance/lance/optimize.pyi
lance/lance/schema.pyi
lance/lance/trace.pyi
lance/log.py
lance/optimize.py
lance/progress.py
lance/query.py
lance/sampler.py
lance/schema.py
lance/tf/__init__.py
lance/tf/data.py
lance/tf/tfrecord.py
lance/torch/__init__.py
lance/torch/async_dataset.py
lance/torch/bench_utils.py
lance/torch/data.py
lance/torch/dist.py
lance/torch/distance.py
lance/torch/kmeans.py
lance/tracing.py
lance/types.py
lance/udf.py
lance/util.py
lance/vector.py
jay_lance-0.38.2.dist-info/RECORD
